mmt_retrieval/__init__.py
mmt_retrieval/mmt.py
mmt_retrieval/retrieval.py
mmt_retrieval/util.py
mmt_retrieval/data/__init__.py
mmt_retrieval/data/datasets.py
mmt_retrieval/data/image_dict.py
mmt_retrieval/evaluation/__init__.py
mmt_retrieval/evaluation/evaluations.py
mmt_retrieval/losses/__init__.py
mmt_retrieval/losses/losses.py
mmt_retrieval/model/__init__.py
mmt_retrieval/model/models.py
mmt_retrieval/multimodal_transformers/__init__.py
mmt_retrieval/multimodal_transformers/m3p/__init__.py
mmt_retrieval/multimodal_transformers/m3p/model/__init__.py
mmt_retrieval/multimodal_transformers/m3p/model/transformer.py
mmt_retrieval/multimodal_transformers/m3p/model/utils.py
mmt_retrieval/multimodal_transformers/oscar/__init__.py
mmt_retrieval/multimodal_transformers/oscar/modeling/__init__.py
mmt_retrieval/multimodal_transformers/oscar/modeling/modeling_bert.py
mmt_retrieval/multimodal_transformers/oscar/modeling/modeling_utils.py
mmt_retrieval/multimodal_transformers/oscar/utils/__init__.py
mmt_retrieval/multimodal_transformers/oscar/utils/caption_evaluate.py
mmt_retrieval/multimodal_transformers/oscar/utils/cbs.py
mmt_retrieval/multimodal_transformers/oscar/utils/logger.py
mmt_retrieval/multimodal_transformers/oscar/utils/misc.py
mmt_retrieval/multimodal_transformers/oscar/utils/task_utils.py
mmt_retrieval/multimodal_transformers/oscar/utils/tsv_file.py
mmt_retrieval/multimodal_transformers/oscar/utils/tsv_file_ops.py
mmt_retrieval/multimodal_transformers/villa/__init__.py
mmt_retrieval/multimodal_transformers/villa/attention.py
mmt_retrieval/multimodal_transformers/villa/itm.py
mmt_retrieval/multimodal_transformers/villa/layer.py
mmt_retrieval/multimodal_transformers/villa/model.py
mmt_retrieval/multimodal_transformers/villa/nlvr2.py
mmt_retrieval/multimodal_transformers/villa/ot.py
mmt_retrieval/multimodal_transformers/villa/pretrain.py
mmt_retrieval/multimodal_transformers/villa/vcr.py
mmt_retrieval/multimodal_transformers/villa/ve.py
mmt_retrieval-0.1.2.dist-info/LICENSE
mmt_retrieval-0.1.2.dist-info/METADATA
mmt_retrieval-0.1.2.dist-info/NOTICE.txt
mmt_retrieval-0.1.2.dist-info/WHEEL
mmt_retrieval-0.1.2.dist-info/top_level.txt
mmt_retrieval-0.1.2.dist-info/RECORD
