Metadata-Version: 2.1
Name: mmt-retrieval
Version: 0.1.2
Summary: Multimodal Transformers for Image-Text Retrieval and more
Home-page: https://github.com/UKPLab/MMT-Retrieval
Author: Gregor Geigle
Author-email: gregor.geigle@gmail.com
License: MIT
Keywords: Transformer Networks Oscar UNITER M3P multimodal embedding PyTorch NLP CV deep learning image search retrieval
Platform: UNKNOWN
Classifier: Development Status :: 4 - Beta
Classifier: Intended Audience :: Science/Research
Classifier: License :: OSI Approved :: MIT License
Classifier: Programming Language :: Python :: 3.6
Classifier: Topic :: Scientific/Engineering :: Artificial Intelligence
License-File: LICENSE
License-File: NOTICE.txt
Requires-Dist: sentence-transformers (<=1.2.1,>=0.4.1.2)
Requires-Dist: tqdm (>=4.32.1)
Requires-Dist: requests (>=2.22.0)
Requires-Dist: transformers (>=4.1.1)
Requires-Dist: numpy (>=1.19.3)
Requires-Dist: torch (>=1.6.0)
